{"nodes": [{"id": "c_users_patri_onedrive_escritorio_kioskstar_tpfinal_backend_src_controllers_stock_controller_ts", "label": "stock.controller.ts", "file_type": "code", "source_file": "C:\\Users\\patri\\OneDrive\\Escritorio\\Kioskstar-TPFINAL\\backend\\src\\controllers\\stock.controller.ts", "source_location": "L1"}, {"id": "controllers_stock_controller_getstockbybranch", "label": "getStockByBranch()", "file_type": "code", "source_file": "C:\\Users\\patri\\OneDrive\\Escritorio\\Kioskstar-TPFINAL\\backend\\src\\controllers\\stock.controller.ts", "source_location": "L5"}, {"id": "controllers_stock_controller_updatestock", "label": "updateStock()", "file_type": "code", "source_file": "C:\\Users\\patri\\OneDrive\\Escritorio\\Kioskstar-TPFINAL\\backend\\src\\controllers\\stock.controller.ts", "source_location": "L26"}], "edges": [{"source": "c_users_patri_onedrive_escritorio_kioskstar_tpfinal_backend_src_controllers_stock_controller_ts", "target": "express", "relation": "imports_from", "context": "import", "confidence": "EXTRACTED", "source_file": "C:\\Users\\patri\\OneDrive\\Escritorio\\Kioskstar-TPFINAL\\backend\\src\\controllers\\stock.controller.ts", "source_location": "L1", "weight": 1.0}, {"source": "c_users_patri_onedrive_escritorio_kioskstar_tpfinal_backend_src_controllers_stock_controller_ts", "target": "c_users_patri_onedrive_escritorio_kioskstar_tpfinal_backend_src_lib_prisma_ts", "relation": "imports_from", "context": "import", "confidence": "EXTRACTED", "source_file": "C:\\Users\\patri\\OneDrive\\Escritorio\\Kioskstar-TPFINAL\\backend\\src\\controllers\\stock.controller.ts", "source_location": "L2", "weight": 1.0}, {"source": "c_users_patri_onedrive_escritorio_kioskstar_tpfinal_backend_src_controllers_stock_controller_ts", "target": "c_users_patri_onedrive_escritorio_kioskstar_tpfinal_backend_src_middlewares_auth_middleware_ts", "relation": "imports_from", "context": "import", "confidence": "EXTRACTED", "source_file": "C:\\Users\\patri\\OneDrive\\Escritorio\\Kioskstar-TPFINAL\\backend\\src\\controllers\\stock.controller.ts", "source_location": "L3", "weight": 1.0}, {"source": "c_users_patri_onedrive_escritorio_kioskstar_tpfinal_backend_src_controllers_stock_controller_ts", "target": "middlewares_auth_middleware_authrequest", "relation": "imports", "context": "import", "confidence": "EXTRACTED", "source_file": "C:\\Users\\patri\\OneDrive\\Escritorio\\Kioskstar-TPFINAL\\backend\\src\\controllers\\stock.controller.ts", "source_location": "L3", "weight": 1.0}, {"source": "c_users_patri_onedrive_escritorio_kioskstar_tpfinal_backend_src_controllers_stock_controller_ts", "target": "controllers_stock_controller_getstockbybranch", "relation": "contains", "confidence": "EXTRACTED", "source_file": "C:\\Users\\patri\\OneDrive\\Escritorio\\Kioskstar-TPFINAL\\backend\\src\\controllers\\stock.controller.ts", "source_location": "L5", "weight": 1.0}, {"source": "c_users_patri_onedrive_escritorio_kioskstar_tpfinal_backend_src_controllers_stock_controller_ts", "target": "controllers_stock_controller_updatestock", "relation": "contains", "confidence": "EXTRACTED", "source_file": "C:\\Users\\patri\\OneDrive\\Escritorio\\Kioskstar-TPFINAL\\backend\\src\\controllers\\stock.controller.ts", "source_location": "L26", "weight": 1.0}], "raw_calls": [{"caller_nid": "controllers_stock_controller_getstockbybranch", "callee": "findMany", "is_member_call": true, "source_file": "C:\\Users\\patri\\OneDrive\\Escritorio\\Kioskstar-TPFINAL\\backend\\src\\controllers\\stock.controller.ts", "source_location": "L9"}, {"caller_nid": "controllers_stock_controller_getstockbybranch", "callee": "parseInt", "is_member_call": false, "source_file": "C:\\Users\\patri\\OneDrive\\Escritorio\\Kioskstar-TPFINAL\\backend\\src\\controllers\\stock.controller.ts", "source_location": "L10"}, {"caller_nid": "controllers_stock_controller_getstockbybranch", "callee": "json", "is_member_call": true, "source_file": "C:\\Users\\patri\\OneDrive\\Escritorio\\Kioskstar-TPFINAL\\backend\\src\\controllers\\stock.controller.ts", "source_location": "L19"}, {"caller_nid": "controllers_stock_controller_getstockbybranch", "callee": "error", "is_member_call": true, "source_file": "C:\\Users\\patri\\OneDrive\\Escritorio\\Kioskstar-TPFINAL\\backend\\src\\controllers\\stock.controller.ts", "source_location": "L21"}, {"caller_nid": "controllers_stock_controller_getstockbybranch", "callee": "json", "is_member_call": true, "source_file": "C:\\Users\\patri\\OneDrive\\Escritorio\\Kioskstar-TPFINAL\\backend\\src\\controllers\\stock.controller.ts", "source_location": "L22"}, {"caller_nid": "controllers_stock_controller_getstockbybranch", "callee": "status", "is_member_call": true, "source_file": "C:\\Users\\patri\\OneDrive\\Escritorio\\Kioskstar-TPFINAL\\backend\\src\\controllers\\stock.controller.ts", "source_location": "L22"}, {"caller_nid": "controllers_stock_controller_updatestock", "callee": "upsert", "is_member_call": true, "source_file": "C:\\Users\\patri\\OneDrive\\Escritorio\\Kioskstar-TPFINAL\\backend\\src\\controllers\\stock.controller.ts", "source_location": "L31"}, {"caller_nid": "controllers_stock_controller_updatestock", "callee": "parseInt", "is_member_call": false, "source_file": "C:\\Users\\patri\\OneDrive\\Escritorio\\Kioskstar-TPFINAL\\backend\\src\\controllers\\stock.controller.ts", "source_location": "L34"}, {"caller_nid": "controllers_stock_controller_updatestock", "callee": "parseInt", "is_member_call": false, "source_file": "C:\\Users\\patri\\OneDrive\\Escritorio\\Kioskstar-TPFINAL\\backend\\src\\controllers\\stock.controller.ts", "source_location": "L35"}, {"caller_nid": "controllers_stock_controller_updatestock", "callee": "parseInt", "is_member_call": false, "source_file": "C:\\Users\\patri\\OneDrive\\Escritorio\\Kioskstar-TPFINAL\\backend\\src\\controllers\\stock.controller.ts", "source_location": "L40"}, {"caller_nid": "controllers_stock_controller_updatestock", "callee": "parseInt", "is_member_call": false, "source_file": "C:\\Users\\patri\\OneDrive\\Escritorio\\Kioskstar-TPFINAL\\backend\\src\\controllers\\stock.controller.ts", "source_location": "L41"}, {"caller_nid": "controllers_stock_controller_updatestock", "callee": "json", "is_member_call": true, "source_file": "C:\\Users\\patri\\OneDrive\\Escritorio\\Kioskstar-TPFINAL\\backend\\src\\controllers\\stock.controller.ts", "source_location": "L51"}, {"caller_nid": "controllers_stock_controller_updatestock", "callee": "error", "is_member_call": true, "source_file": "C:\\Users\\patri\\OneDrive\\Escritorio\\Kioskstar-TPFINAL\\backend\\src\\controllers\\stock.controller.ts", "source_location": "L53"}, {"caller_nid": "controllers_stock_controller_updatestock", "callee": "json", "is_member_call": true, "source_file": "C:\\Users\\patri\\OneDrive\\Escritorio\\Kioskstar-TPFINAL\\backend\\src\\controllers\\stock.controller.ts", "source_location": "L54"}, {"caller_nid": "controllers_stock_controller_updatestock", "callee": "status", "is_member_call": true, "source_file": "C:\\Users\\patri\\OneDrive\\Escritorio\\Kioskstar-TPFINAL\\backend\\src\\controllers\\stock.controller.ts", "source_location": "L54"}]}